DC_WORKSHOP/verilog_files/lab1_flop_with_en.v
module lab1_flop_with_en ( input res , input clk , input d , input en , output reg q);
always @ (posedge clk , posedge res)
begin
	if(res)
		q <= 1'b0;
	else if(en)
		q <= d;	
end
endmodule

DC_WORKSHOP/verilog_files/tb_lab1_flop_with_en.v
`timescale 1ns / 1ps
module tb_lab1_flop_with_en ();

reg clk , d , res, en;
wire q;

lab1_flop_with_en uut (
	.clk (clk),
	.res(res),
	.d(d),
	.en(en),
	.q(q));

initial 
begin
	$dumpfile("tb_lab1_flop_with_en.vcd");
	$dumpvars(0,tb_lab1_flop_with_en);
	clk = 1'b0;
	d = 1'b0;
	en = 1'b0;
	res = 1'b1; # 200;
	res = 1'b0;
	#3000 $finish;
end

always #10 clk = ~clk;
always #33 d = ~d;
always #77 en = ~en; 

endmodule

DC_WORKSHOP/verilog_files/tb_lab1_flop_with_en.vcd
$date
	Sun Aug  1 11:02:30 2021
$end
$version
	Icarus Verilog
$end
$timescale
	1ps
$end
$scope module tb_lab1_flop_with_en $end
$var wire 1 ! q $end
$var reg 1 " clk $end
$var reg 1 # d $end
$var reg 1 $ en $end
$var reg 1 % res $end
$scope module uut $end
$var wire 1 " clk $end
$var wire 1 # d $end
$var wire 1 $ en $end
$var wire 1 % res $end
$var reg 1 ! q $end
$upscope $end
$upscope $end
$enddefinitions $end
#0
$dumpvars
1%
0$
0#
0"
0!
$end
#10000
1"
#20000
0"
#30000
1"
#33000
1#
#40000
0"
#50000
1"
#60000
0"
#66000
0#
#70000
1"
#77000
1$
#80000
0"
#90000
1"
#99000
1#
#100000
0"
#110000
1"
#120000
0"
#130000
1"
#132000
0#
#140000
0"
#150000
1"
#154000
0$
#160000
0"
#165000
1#
#170000
1"
#180000
0"
#190000
1"
#198000
0#
#200000
0"
0%
#210000
1"
#220000
0"
#230000
1"
#231000
1#
1$
#240000
0"
#250000
1!
1"
#260000
0"
#264000
0#
#270000
0!
1"
#280000
0"
#290000
1"
#297000
1#
#300000
0"
#308000
0$
#310000
1"
#320000
0"
#330000
1"
0#
#340000
0"
#350000
1"
#360000
0"
#363000
1#
#370000
1"
#380000
0"
#385000
1$
#390000
1!
1"
#396000
0#
#400000
0"
#410000
0!
1"
#420000
0"
#429000
1#
#430000
1!
1"
#440000
0"
#450000
1"
#460000
0"
#462000
0#
0$
#470000
1"
#480000
0"
#490000
1"
#495000
1#
#500000
0"
#510000
1"
#520000
0"
#528000
0#
#530000
1"
#539000
1$
#540000
0"
#550000
0!
1"
#560000
0"
#561000
1#
#570000
1!
1"
#580000
0"
#590000
1"
#594000
0#
#600000
0"
#610000
0!
1"
#616000
0$
#620000
0"
#627000
1#
#630000
1"
#640000
0"
#650000
1"
#660000
0"
0#
#670000
1"
#680000
0"
#690000
1"
#693000
1#
1$
#700000
0"
#710000
1!
1"
#720000
0"
#726000
0#
#730000
0!
1"
#740000
0"
#750000
1"
#759000
1#
#760000
0"
#770000
1"
0$
#780000
0"
#790000
1"
#792000
0#
#800000
0"
#810000
1"
#820000
0"
#825000
1#
#830000
1"
#840000
0"
#847000
1$
#850000
1!
1"
#858000
0#
#860000
0"
#870000
0!
1"
#880000
0"
#890000
1"
#891000
1#
#900000
0"
#910000
1!
1"
#920000
0"
#924000
0#
0$
#930000
1"
#940000
0"
#950000
1"
#957000
1#
#960000
0"
#970000
1"
#980000
0"
#990000
1"
0#
#1000000
0"
#1001000
1$
#1010000
0!
1"
#1020000
0"
#1023000
1#
#1030000
1!
1"
#1040000
0"
#1050000
1"
#1056000
0#
#1060000
0"
#1070000
0!
1"
#1078000
0$
#1080000
0"
#1089000
1#
#1090000
1"
#1100000
0"
#1110000
1"
#1120000
0"
#1122000
0#
#1130000
1"
#1140000
0"
#1150000
1"
#1155000
1#
1$
#1160000
0"
#1170000
1!
1"
#1180000
0"
#1188000
0#
#1190000
0!
1"
#1200000
0"
#1210000
1"
#1220000
0"
#1221000
1#
#1230000
1!
1"
#1232000
0$
#1240000
0"
#1250000
1"
#1254000
0#
#1260000
0"
#1270000
1"
#1280000
0"
#1287000
1#
#1290000
1"
#1300000
0"
#1309000
1$
#1310000
1"
#1320000
0"
0#
#1330000
0!
1"
#1340000
0"
#1350000
1"
#1353000
1#
#1360000
0"
#1370000
1!
1"
#1380000
0"
#1386000
0#
0$
#1390000
1"
#1400000
0"
#1410000
1"
#1419000
1#
#1420000
0"
#1430000
1"
#1440000
0"
#1450000
1"
#1452000
0#
#1460000
0"
#1463000
1$
#1470000
0!
1"
#1480000
0"
#1485000
1#
#1490000
1!
1"
#1500000
0"
#1510000
1"
#1518000
0#
#1520000
0"
#1530000
0!
1"
#1540000
0"
0$
#1550000
1"
#1551000
1#
#1560000
0"
#1570000
1"
#1580000
0"
#1584000
0#
#1590000
1"
#1600000
0"
#1610000
1"
#1617000
1#
1$
#1620000
0"
#1630000
1!
1"
#1640000
0"
#1650000
0!
1"
0#
#1660000
0"
#1670000
1"
#1680000
0"
#1683000
1#
#1690000
1!
1"
#1694000
0$
#1700000
0"
#1710000
1"
#1716000
0#
#1720000
0"
#1730000
1"
#1740000
0"
#1749000
1#
#1750000
1"
#1760000
0"
#1770000
1"
#1771000
1$
#1780000
0"
#1782000
0#
#1790000
0!
1"
#1800000
0"
#1810000
1"
#1815000
1#
#1820000
0"
#1830000
1!
1"
#1840000
0"
#1848000
0#
0$
#1850000
1"
#1860000
0"
#1870000
1"
#1880000
0"
#1881000
1#
#1890000
1"
#1900000
0"
#1910000
1"
#1914000
0#
#1920000
0"
#1925000
1$
#1930000
0!
1"
#1940000
0"
#1947000
1#
#1950000
1!
1"
#1960000
0"
#1970000
1"
#1980000
0"
0#
#1990000
0!
1"
#2000000
0"
#2002000
0$
#2010000
1"
#2013000
1#
#2020000
0"
#2030000
1"
#2040000
0"
#2046000
0#
#2050000
1"
#2060000
0"
#2070000
1"
#2079000
1#
1$
#2080000
0"
#2090000
1!
1"
#2100000
0"
#2110000
1"
#2112000
0#
#2120000
0"
#2130000
0!
1"
#2140000
0"
#2145000
1#
#2150000
1!
1"
#2156000
0$
#2160000
0"
#2170000
1"
#2178000
0#
#2180000
0"
#2190000
1"
#2200000
0"
#2210000
1"
#2211000
1#
#2220000
0"
#2230000
1"
#2233000
1$
#2240000
0"
#2244000
0#
#2250000
0!
1"
#2260000
0"
#2270000
1"
#2277000
1#
#2280000
0"
#2290000
1!
1"
#2300000
0"
#2310000
1"
0#
0$
#2320000
0"
#2330000
1"
#2340000
0"
#2343000
1#
#2350000
1"
#2360000
0"
#2370000
1"
#2376000
0#
#2380000
0"
#2387000
1$
#2390000
0!
1"
#2400000
0"
#2409000
1#
#2410000
1!
1"
#2420000
0"
#2430000
1"
#2440000
0"
#2442000
0#
#2450000
0!
1"
#2460000
0"
#2464000
0$
#2470000
1"
#2475000
1#
#2480000
0"
#2490000
1"
#2500000
0"
#2508000
0#
#2510000
1"
#2520000
0"
#2530000
1"
#2540000
0"
#2541000
1#
1$
#2550000
1!
1"
#2560000
0"
#2570000
1"
#2574000
0#
#2580000
0"
#2590000
0!
1"
#2600000
0"
#2607000
1#
#2610000
1!
1"
#2618000
0$
#2620000
0"
#2630000
1"
#2640000
0"
0#
#2650000
1"
#2660000
0"
#2670000
1"
#2673000
1#
#2680000
0"
#2690000
1"
#2695000
1$
#2700000
0"
#2706000
0#
#2710000
0!
1"
#2720000
0"
#2730000
1"
#2739000
1#
#2740000
0"
#2750000
1!
1"
#2760000
0"
#2770000
1"
#2772000
0#
0$
#2780000
0"
#2790000
1"
#2800000
0"
#2805000
1#
#2810000
1"
#2820000
0"
#2830000
1"
#2838000
0#
#2840000
0"
#2849000
1$
#2850000
0!
1"
#2860000
0"
#2870000
1"
#2871000
1#
#2880000
0"
#2890000
1!
1"
#2900000
0"
#2904000
0#
#2910000
0!
1"
#2920000
0"
#2926000
0$
#2930000
1"
#2937000
1#
#2940000
0"
#2950000
1"
#2960000
0"
#2970000
1"
0#
#2980000
0"
#2990000
1"
#3000000
0"
#3003000
1#
1$
#3010000
1!
1"
#3020000
0"
#3030000
1"
#3036000
0#
#3040000
0"
#3050000
0!
1"
#3060000
0"
#3069000
1#
#3070000
1!
1"
#3080000
0"
0$
#3090000
1"
#3100000
0"
#3102000
0#
#3110000
1"
#3120000
0"
#3130000
1"
#3135000
1#
#3140000
0"
#3150000
1"
#3157000
1$
#3160000
0"
#3168000
0#
#3170000
0!
1"
